pygom/__init__.py
pygom/approximate_bayesian_computation/__init__.py
pygom/approximate_bayesian_computation/approximate_bayesian_computation.py
pygom/data/eg1.json
pygom/loss/.gitignore
pygom/loss/__init__.py
pygom/loss/base_loss.py
pygom/loss/confidence_interval.py
pygom/loss/epijson_loss.py
pygom/loss/get_init.py
pygom/loss/loss_type.py
pygom/loss/ode_loss.py
pygom/loss/read_epijson.py
pygom/model/__init__.py
pygom/model/_model_errors.py
pygom/model/_model_verification.py
pygom/model/_ode_composition.py
pygom/model/_tau_leap.cp312-win_amd64.pyd
pygom/model/_tau_leap.pyx
pygom/model/_transition_graph.py
pygom/model/base_ode_model.py
pygom/model/common_models.py
pygom/model/deterministic.py
pygom/model/epi_analysis.py
pygom/model/ode_variable.py
pygom/model/simulate.py
pygom/model/stochastic_simulation.py
pygom/model/transition.py
pygom/model/ode_utils/__init__.py
pygom/model/ode_utils/checks_and_conversions.py
pygom/model/ode_utils/compile_canary.py
pygom/model/ode_utils/plot_det.py
pygom/model/ode_utils/plot_stoc.py
pygom/utilR/__init__.py
pygom/utilR/distn.py
pygom-0.1.8.dist-info/LICENSE.txt
pygom-0.1.8.dist-info/METADATA
pygom-0.1.8.dist-info/WHEEL
pygom-0.1.8.dist-info/top_level.txt
pygom-0.1.8.dist-info/RECORD
