Metadata-Version: 2.1
Name: pygom
Version: 0.1.8
Summary: ODE modeling in Python.
Author: Edwin Tye, Hannah Williams, Jonty Carruthers, Martin Grunnill
Author-email: Thomas Finnie <thomas.finnie@ukhsa.gov.uk>, Joe Gibson <joseph.gibson@ukhsa.gov.uk>
Project-URL: Homepage, http://ukhsa-collaboration.github.io/pygom/md/intro.html
Project-URL: Issues, https://github.com/ukhsa-collaboration/pygom/issues
Classifier: Programming Language :: Python :: 3
Classifier: License :: OSI Approved :: GNU General Public License v2 (GPLv2)
Classifier: Operating System :: Microsoft :: Windows
Classifier: Operating System :: POSIX
Classifier: Programming Language :: Python :: 3.9
Classifier: Programming Language :: Python :: 3.10
Classifier: Programming Language :: Python :: 3.11
Classifier: Programming Language :: Python :: 3.12
Classifier: Topic :: Scientific/Engineering
Classifier: Topic :: Scientific/Engineering :: Mathematics
Classifier: Topic :: Scientific/Engineering :: Physics
Classifier: Development Status :: 5 - Production/Stable
Requires-Python: >=3.9
License-File: LICENSE.txt
Requires-Dist: setuptools >=64
Requires-Dist: setuptools-scm >=8
Requires-Dist: setuptools-scm-git-archive
Requires-Dist: dask[complete] >=0.13.0
Requires-Dist: graphviz >=0.4.9
Requires-Dist: matplotlib >=1.0.0
Requires-Dist: numpy >=1.24.4
Requires-Dist: pandas >=2.2.2
Requires-Dist: python-dateutil >=2.0.0
Requires-Dist: scipy >=1.10.1
Requires-Dist: sympy >=1.0.0
Requires-Dist: numpydoc >=0.6.0
Requires-Dist: cython >=0.29
